odoo/addons/project_task_link/README.rst
odoo/addons/project_task_link/__init__.py
odoo/addons/project_task_link/__manifest__.py
odoo/addons/project_task_link/i18n/it.po
odoo/addons/project_task_link/i18n/project_task_link.pot
odoo/addons/project_task_link/i18n/pt_BR.po
odoo/addons/project_task_link/models/__init__.py
odoo/addons/project_task_link/models/project_project.py
odoo/addons/project_task_link/readme/DESCRIPTION.rst
odoo/addons/project_task_link/static/description/icon.png
odoo/addons/project_task_link/static/description/index.html
odoo/addons/project_task_link/views/project_project_views.xml
odoo_addon_project_task_link-16.0.1.0.1.dist-info/METADATA
odoo_addon_project_task_link-16.0.1.0.1.dist-info/WHEEL
odoo_addon_project_task_link-16.0.1.0.1.dist-info/top_level.txt
odoo_addon_project_task_link-16.0.1.0.1.dist-info/RECORD
